ptyme_track/__init__.py
ptyme_track/cement.py
ptyme_track/client.py
ptyme_track/cur_times.py
ptyme_track/git_ci_diff.py
ptyme_track/main.py
ptyme_track/ptyme_env.py
ptyme_track/secret.py
ptyme_track/server.py
ptyme_track/signature.py
ptyme_track/signed_time.py
ptyme_track/time_blocks.py
ptyme_track/validation.py
ptyme_track-0.3.0.dist-info/LICENSE
ptyme_track-0.3.0.dist-info/METADATA
ptyme_track-0.3.0.dist-info/WHEEL
ptyme_track-0.3.0.dist-info/entry_points.txt
ptyme_track-0.3.0.dist-info/RECORD
