Metadata-Version: 2.1
Name: ptyme-track
Version: 0.3.0
Summary: The obnoxiously named time tracking based on file modifications and signed reporting. The P is silent like in Pterodactyl
License: MIT
Author: James Hutchison
Author-email: JamesGHutchison@proton.me
Requires-Python: >=3.8,<4.0
Classifier: License :: OSI Approved :: MIT License
Classifier: Programming Language :: Python :: 3
Classifier: Programming Language :: Python :: 3.8
Classifier: Programming Language :: Python :: 3.9
Classifier: Programming Language :: Python :: 3.10
Classifier: Programming Language :: Python :: 3.11
